topsis_anshika_102317059/__init__.py
topsis_anshika_102317059/cli.py
topsis_anshika_102317059/topsis_logic.py
topsis_anshika_102317059-1.0.0.dist-info/licenses/LICENSE
topsis_anshika_102317059-1.0.0.dist-info/METADATA
topsis_anshika_102317059-1.0.0.dist-info/WHEEL
topsis_anshika_102317059-1.0.0.dist-info/entry_points.txt
topsis_anshika_102317059-1.0.0.dist-info/top_level.txt
topsis_anshika_102317059-1.0.0.dist-info/RECORD
