Metadata-Version: 2.4
Name: topsis-anshika-102317059
Version: 1.0.0
Summary: TOPSIS implementation as CLI tool
Author-email: Anshika <anshikaahuja6487@gmail.com>
License: MIT
Requires-Python: >=3.8
License-File: LICENSE
Requires-Dist: pandas
Requires-Dist: numpy
Dynamic: license-file
